{
	"info": {
		"_postman_id": "f2dceee0-aff8-4b32-b01d-a5fc94031f2a",
		"name": "LMS",
		"schema": "https://schema.getpostman.com/json/collection/v2.1.0/collection.json",
		"_exporter_id": "12617441"
	},
	"item": [
		{
			"name": "course",
			"item": [
				{
					"name": "Add",
					"request": {
						"method": "POST",
						"header": [],
						"body": {
							"mode": "raw",
							"raw": "{\r\n  \"name\": \"Dummy Course\",\r\n  \"code\": \"D123\",\r\n  \"desc\": \"This is a sample course description.\"\r\n}\r\n",
							"options": {
								"raw": {
									"language": "json"
								}
							}
						},
						"url": {
							"raw": "http://localhost:8080/api/v1/course/register",
							"protocol": "http",
							"host": [
								"localhost"
							],
							"port": "8080",
							"path": [
								"api",
								"v1",
								"course",
								"register"
							]
						}
					},
					"response": []
				},
				{
					"name": "delete",
					"request": {
						"method": "GET",
						"header": [],
						"url": {
							"raw": "http://localhost:8080/api/v1/course",
							"protocol": "http",
							"host": [
								"localhost"
							],
							"port": "8080",
							"path": [
								"api",
								"v1",
								"course"
							]
						}
					},
					"response": []
				},
				{
					"name": "get",
					"request": {
						"method": "GET",
						"header": [],
						"url": {
							"raw": "http://localhost:8080/api/v1/course",
							"protocol": "http",
							"host": [
								"localhost"
							],
							"port": "8080",
							"path": [
								"api",
								"v1",
								"course"
							]
						}
					},
					"response": []
				},
				{
					"name": "update",
					"request": {
						"method": "GET",
						"header": []
					},
					"response": []
				}
			]
		},
		{
			"name": "teacher",
			"item": [
				{
					"name": "Add",
					"request": {
						"method": "POST",
						"header": [],
						"body": {
							"mode": "raw",
							"raw": "{\r\n  \"name\": \"Dummy Course\",\r\n  \"code\": \"D123\",\r\n  \"desc\": \"This is a sample course description.\"\r\n}\r\n",
							"options": {
								"raw": {
									"language": "json"
								}
							}
						},
						"url": {
							"raw": "http://localhost:8080/api/v1/course/register",
							"protocol": "http",
							"host": [
								"localhost"
							],
							"port": "8080",
							"path": [
								"api",
								"v1",
								"course",
								"register"
							]
						}
					},
					"response": []
				},
				{
					"name": "delete",
					"request": {
						"method": "GET",
						"header": [],
						"url": {
							"raw": "http://localhost:8080/api/v1/course",
							"protocol": "http",
							"host": [
								"localhost"
							],
							"port": "8080",
							"path": [
								"api",
								"v1",
								"course"
							]
						}
					},
					"response": []
				},
				{
					"name": "get",
					"request": {
						"method": "GET",
						"header": [],
						"url": {
							"raw": "http://localhost:8080/api/v1/course",
							"protocol": "http",
							"host": [
								"localhost"
							],
							"port": "8080",
							"path": [
								"api",
								"v1",
								"course"
							]
						}
					},
					"response": []
				},
				{
					"name": "update",
					"request": {
						"method": "GET",
						"header": []
					},
					"response": []
				},
				{
					"name": "teach course",
					"request": {
						"method": "POST",
						"header": [],
						"body": {
							"mode": "raw",
							"raw": "{\r\n  \"name\": \"Dummy Course\",\r\n  \"code\": \"D123\",\r\n  \"desc\": \"This is a sample course description.\"\r\n}\r\n",
							"options": {
								"raw": {
									"language": "json"
								}
							}
						},
						"url": {
							"raw": "http://localhost:8080/api/v1/course/register",
							"protocol": "http",
							"host": [
								"localhost"
							],
							"port": "8080",
							"path": [
								"api",
								"v1",
								"course",
								"register"
							]
						}
					},
					"response": []
				},
				{
					"name": "withdraw course",
					"request": {
						"method": "POST",
						"header": [],
						"body": {
							"mode": "raw",
							"raw": "{\r\n  \"name\": \"Dummy Course\",\r\n  \"code\": \"D123\",\r\n  \"desc\": \"This is a sample course description.\"\r\n}\r\n",
							"options": {
								"raw": {
									"language": "json"
								}
							}
						},
						"url": {
							"raw": "http://localhost:8080/api/v1/course/register",
							"protocol": "http",
							"host": [
								"localhost"
							],
							"port": "8080",
							"path": [
								"api",
								"v1",
								"course",
								"register"
							]
						}
					},
					"response": []
				}
			]
		},
		{
			"name": "student",
			"item": [
				{
					"name": "Add",
					"request": {
						"method": "POST",
						"header": [],
						"body": {
							"mode": "raw",
							"raw": "{\r\n  \"name\": \"Dummy Course\",\r\n  \"code\": \"D123\",\r\n  \"desc\": \"This is a sample course description.\"\r\n}\r\n",
							"options": {
								"raw": {
									"language": "json"
								}
							}
						},
						"url": {
							"raw": "http://localhost:8080/api/v1/course/register",
							"protocol": "http",
							"host": [
								"localhost"
							],
							"port": "8080",
							"path": [
								"api",
								"v1",
								"course",
								"register"
							]
						}
					},
					"response": []
				},
				{
					"name": "delete",
					"request": {
						"method": "GET",
						"header": [],
						"url": {
							"raw": "http://localhost:8080/api/v1/course",
							"protocol": "http",
							"host": [
								"localhost"
							],
							"port": "8080",
							"path": [
								"api",
								"v1",
								"course"
							]
						}
					},
					"response": []
				},
				{
					"name": "get",
					"request": {
						"method": "GET",
						"header": [],
						"url": {
							"raw": "http://localhost:8080/api/v1/course",
							"protocol": "http",
							"host": [
								"localhost"
							],
							"port": "8080",
							"path": [
								"api",
								"v1",
								"course"
							]
						}
					},
					"response": []
				},
				{
					"name": "update",
					"request": {
						"method": "GET",
						"header": []
					},
					"response": []
				},
				{
					"name": "enroll in course",
					"request": {
						"method": "POST",
						"header": [],
						"body": {
							"mode": "raw",
							"raw": "{\r\n  \"name\": \"Dummy Course\",\r\n  \"code\": \"D123\",\r\n  \"desc\": \"This is a sample course description.\"\r\n}\r\n",
							"options": {
								"raw": {
									"language": "json"
								}
							}
						},
						"url": {
							"raw": "http://localhost:8080/api/v1/course/register",
							"protocol": "http",
							"host": [
								"localhost"
							],
							"port": "8080",
							"path": [
								"api",
								"v1",
								"course",
								"register"
							]
						}
					},
					"response": []
				},
				{
					"name": "Withdraw course",
					"request": {
						"method": "POST",
						"header": [],
						"body": {
							"mode": "raw",
							"raw": "{\r\n  \"name\": \"Dummy Course\",\r\n  \"code\": \"D123\",\r\n  \"desc\": \"This is a sample course description.\"\r\n}\r\n",
							"options": {
								"raw": {
									"language": "json"
								}
							}
						},
						"url": {
							"raw": "http://localhost:8080/api/v1/course/register",
							"protocol": "http",
							"host": [
								"localhost"
							],
							"port": "8080",
							"path": [
								"api",
								"v1",
								"course",
								"register"
							]
						}
					},
					"response": []
				}
			]
		},
		{
			"name": "authentication",
			"item": [
				{
					"name": "Authentication",
					"request": {
						"method": "POST",
						"header": [],
						"body": {
							"mode": "raw",
							"raw": "{\r\n    \"username\": \"admin\",\r\n    \"password\": \"test1234\"\r\n}",
							"options": {
								"raw": {
									"language": "json"
								}
							}
						},
						"url": {
							"raw": "https://dentistsystem.azurewebsites.net/api/v1/auth",
							"protocol": "https",
							"host": [
								"dentistsystem",
								"azurewebsites",
								"net"
							],
							"path": [
								"api",
								"v1",
								"auth"
							]
						}
					},
					"response": []
				}
			]
		}
	]
}